lzma_cf/__init__.py
lzma_cf/__pypy__.py
lzma_cf/_lzma.py
lzma_cf/_lzma_build.py
lzma_cf/_lzma_cffi.abi3.so
lzma_cf.libs/liblzma-8f5fda0f.so.5.8.1
lzma_cf-0.0.4.dist-info/METADATA
lzma_cf-0.0.4.dist-info/WHEEL
lzma_cf-0.0.4.dist-info/top_level.txt
lzma_cf-0.0.4.dist-info/RECORD
lzma_cf-0.0.4.dist-info/licenses/LICENSES/BSD-3-Clause.txt
lzma_cf-0.0.4.dist-info/licenses/LICENSES/MIT.txt
lzma_cf-0.0.4.dist-info/licenses/LICENSES/PSF-2.0.txt
