Metadata-Version: 2.4
Name: lzma-cf
Version: 0.0.4
Summary: LZMA and XZ compression for control freaks
Author-email: Alex Willmer <alex@moreati.org.uk>
License-Expression: BSD-3-Clause AND MIT AND PSF-2.0
Project-URL: Homepage, https://github.com/moreati/lzma-cf
Keywords: compression,lzma,xz,xz-utils
Classifier: Development Status :: 3 - Alpha
Classifier: Intended Audience :: Developers
Classifier: Programming Language :: Python :: 3
Classifier: Programming Language :: Python :: 3.10
Classifier: Programming Language :: Python :: 3.11
Classifier: Programming Language :: Python :: 3.12
Classifier: Programming Language :: Python :: 3.13
Classifier: Programming Language :: Python :: 3.14
Classifier: Programming Language :: Python :: 3 :: Only
Classifier: Topic :: System :: Archiving :: Compression
Requires-Python: >=3.10
License-File: LICENSES/BSD-3-Clause.txt
License-File: LICENSES/MIT.txt
License-File: LICENSES/PSF-2.0.txt
Requires-Dist: cffi>=1.15; python_version == "3.10" or python_version == "3.11"
Requires-Dist: cffi>=1.16; python_version == "3.12" or python_version == "3.13"
Requires-Dist: cffi>=2.0; python_version >= "3.14"
Dynamic: license-file
